README.md
setup.py
mockerinho/__init__.py
mockerinho/__main__.py
mockerinho/app.py
mockerinho/cli.py
mockerinho/errors.py
mockerinho/matchers.py
mockerinho/simulator.py
mockerinho/utils.py
mockerinho.egg-info/PKG-INFO
mockerinho.egg-info/SOURCES.txt
mockerinho.egg-info/dependency_links.txt
mockerinho.egg-info/entry_points.txt
mockerinho.egg-info/requires.txt
mockerinho.egg-info/top_level.txt
mockerinho/config/__init__.py
mockerinho/config/parser.py
mockerinho/config/schema.py
mockerinho/config/validators.py