Metadata-Version: 2.1
Name: mockerinho
Version: 0.2.1
Summary: Lightweight tool designed to simulate web API endpoints.
Home-page: https://github.com/mockerinho/mockerinho
Author: Mikhail Eremeev
Author-email: meremeev@sfedu.ru
License: MIT
Project-URL: Issues, https://github.com/mockerinho/mockerinho/issues
Project-URL: Sources, https://github.com/mockerinho/mockerinho
Platform: any
Requires-Python: >=3.7,<=3.10
